<?xml version="1.0" encoding="utf-8"?>
<odoo>
    <data>

        <!-- Main Hotel Menu -->
        <menuitem id="menu_hotel_main" 
                  name="Hotel Management" 
                  web_icon="modulio_hotelcore,static/description/icon.png"
                  sequence="10"
                  groups="modulio_hotelcore.group_hotel_user"/>

        <!-- Hotel Configuration Menu -->
        <menuitem id="menu_hotel_config" 
                  name="Configuration" 
                  parent="menu_hotel_main" 
                  sequence="30"/>

        <!-- Hotel Floors Menu -->
        <menuitem id="menu_hotel_floor" 
                  name="Hotel Floors" 
                  parent="menu_hotel_config" 
                  action="action_hotel_floor_act_window" 
                  sequence="5"
                  groups="modulio_hotelcore.group_hotel_user"/>

        <!-- Room Types Menu -->
        <menuitem id="menu_hotel_room_type" 
                  name="Room Types" 
                  parent="menu_hotel_config" 
                  action="action_hotel_room_type_act_window" 
                  sequence="10"
                  groups="modulio_hotelcore.group_hotel_user"/>

        <!-- Rooms Menu -->
        <menuitem id="menu_hotel_room" 
                  name="Rooms" 
                  parent="menu_hotel_main" 
                  action="action_hotel_room_act_window" 
                  sequence="20"
                  groups="modulio_hotelcore.group_hotel_user"/>


        <!-- Room Blocking Menu -->
        <menuitem id="menu_hotel_room_blocking" 
                  name="Room Blocking" 
                  parent="menu_hotel_config" 
                  action="action_hotel_room_blocking_act_window" 
                  sequence="20"
                  groups="modulio_hotelcore.group_hotel_user"/>

        <!-- Room Status History Menu -->
        <menuitem id="menu_hotel_room_status_history" 
                  name="Room Status History" 
                  parent="menu_hotel_main" 
                  action="action_hotel_room_status_history_act_window" 
                  sequence="30"
                  groups="modulio_hotelcore.group_hotel_user"/>

        <!-- Hotel Configuration Menu -->
        <menuitem id="menu_hotel_configuration" 
                  name="Hotel Configuration" 
                  parent="menu_hotel_config" 
                  action="action_hotel_configuration_act_window" 
                  sequence="5"
                  groups="modulio_hotelcore.group_hotel_manager"/>

        <!-- Settings Shortcut -->
        <record id="action_modulio_hotelcore_settings" model="ir.actions.act_window">
          <field name="name">Hotel Core Settings</field>
          <field name="res_model">res.config.settings</field>
          <field name="view_mode">form</field>
          <field name="target">inline</field>
          <field name="context">{'module': 'modulio_hotelcore', 'bin_size': False}</field>
        </record>

        <menuitem id="menu_settings_modulio_hotelcore"
                  name="Settings"
                  parent="menu_hotel_config"
                  action="action_modulio_hotelcore_settings"
                  sequence="99"
                  groups="base.group_system"/>

        <!-- Dashboard Menu -->
        <menuitem id="menu_hotel_dashboard" 
                  name="Dashboard" 
                  parent="menu_hotel_main" 
                  action="action_hotel_dashboard_client" 
                  sequence="1"
                  groups="modulio_hotelcore.group_hotel_user"/>

    </data>
</odoo>
